[
  {
    "model": "militares.previsaovaga",
    "pk": 1,
    "fields": {
      "posto": "1T",
      "quadro": "COMB",
      "efetivo_atual": 15,
      "efetivo_previsto": 50,
      "vagas_disponiveis": 35,
      "vagas_fixadas": 0,
      "observacoes_vagas_fixadas": null,
      "ativo": true,
      "data_criacao": "2025-07-22T18:53:29.991Z",
      "data_atualizacao": "2025-07-25T15:49:33.207Z"
    }
  },
  {
    "model": "militares.previsaovaga",
    "pk": 2,
    "fields": {
      "posto": "2T",
      "quadro": "COMB",
      "efetivo_atual": 29,
      "efetivo_previsto": 56,
      "vagas_disponiveis": 27,
      "vagas_fixadas": 0,
      "observacoes_vagas_fixadas": null,
      "ativo": true,
      "data_criacao": "2025-07-22T18:53:30.005Z",
      "data_atualizacao": "2025-07-25T15:03:08.671Z"
    }
  },
  {
    "model": "militares.previsaovaga",
    "pk": 3,
    "fields": {
      "posto": "CB",
      "quadro": "COMB",
      "efetivo_atual": 6,
      "efetivo_previsto": 6,
      "vagas_disponiveis": 0,
      "vagas_fixadas": 0,
      "observacoes_vagas_fixadas": null,
      "ativo": true,
      "data_criacao": "2025-07-22T18:53:30.005Z",
      "data_atualizacao": "2025-07-28T11:31:37.518Z"
    }
  },
  {
    "model": "militares.previsaovaga",
    "pk": 4,
    "fields": {
      "posto": "CP",
      "quadro": "COMB",
      "efetivo_atual": 10,
      "efetivo_previsto": 38,
      "vagas_disponiveis": 28,
      "vagas_fixadas": 0,
      "observacoes_vagas_fixadas": null,
      "ativo": true,
      "data_criacao": "2025-07-22T18:53:30.014Z",
      "data_atualizacao": "2025-07-25T15:48:35.207Z"
    }
  },
  {
    "model": "militares.previsaovaga",
    "pk": 5,
    "fields": {
      "posto": "MJ",
      "quadro": "COMB",
      "efetivo_atual": 7,
      "efetivo_previsto": 35,
      "vagas_disponiveis": 28,
      "vagas_fixadas": 0,
      "observacoes_vagas_fixadas": null,
      "ativo": true,
      "data_criacao": "2025-07-22T18:53:30.016Z",
      "data_atualizacao": "2025-07-25T15:03:11.318Z"
    }
  },
  {
    "model": "militares.previsaovaga",
    "pk": 6,
    "fields": {
      "posto": "TC",
      "quadro": "COMB",
      "efetivo_atual": 13,
      "efetivo_previsto": 16,
      "vagas_disponiveis": 3,
      "vagas_fixadas": 0,
      "observacoes_vagas_fixadas": null,
      "ativo": true,
      "data_criacao": "2025-07-22T18:53:30.018Z",
      "data_atualizacao": "2025-07-25T15:48:01.188Z"
    }
  },
  {
    "model": "militares.previsaovaga",
    "pk": 7,
    "fields": {
      "posto": "1T",
      "quadro": "COMP",
      "efetivo_atual": 36,
      "efetivo_previsto": 36,
      "vagas_disponiveis": 0,
      "vagas_fixadas": 0,
      "observacoes_vagas_fixadas": null,
      "ativo": true,
      "data_criacao": "2025-07-22T18:53:30.025Z",
      "data_atualizacao": "2025-07-25T15:49:32.219Z"
    }
  },
  {
    "model": "militares.previsaovaga",
    "pk": 8,
    "fields": {
      "posto": "2T",
      "quadro": "COMP",
      "efetivo_atual": 29,
      "efetivo_previsto": 41,
      "vagas_disponiveis": 12,
      "vagas_fixadas": 0,
      "observacoes_vagas_fixadas": null,
      "ativo": true,
      "data_criacao": "2025-07-22T18:53:30.025Z",
      "data_atualizacao": "2025-07-25T15:50:01.775Z"
    }
  },
  {
    "model": "militares.previsaovaga",
    "pk": 9,
    "fields": {
      "posto": "CP",
      "quadro": "COMP",
      "efetivo_atual": 21,
      "efetivo_previsto": 24,
      "vagas_disponiveis": 3,
      "vagas_fixadas": 0,
      "observacoes_vagas_fixadas": null,
      "ativo": true,
      "data_criacao": "2025-07-22T18:53:30.025Z",
      "data_atualizacao": "2025-07-25T15:48:41.071Z"
    }
  },
  {
    "model": "militares.previsaovaga",
    "pk": 10,
    "fields": {
      "posto": "MJ",
      "quadro": "COMP",
      "efetivo_atual": 6,
      "efetivo_previsto": 6,
      "vagas_disponiveis": 0,
      "vagas_fixadas": 0,
      "observacoes_vagas_fixadas": null,
      "ativo": true,
      "data_criacao": "2025-07-22T18:53:30.025Z",
      "data_atualizacao": "2025-07-28T13:30:34.986Z"
    }
  },
  {
    "model": "militares.previsaovaga",
    "pk": 11,
    "fields": {
      "posto": "1T",
      "quadro": "ENG",
      "efetivo_atual": 0,
      "efetivo_previsto": 2,
      "vagas_disponiveis": 2,
      "vagas_fixadas": 0,
      "observacoes_vagas_fixadas": null,
      "ativo": true,
      "data_criacao": "2025-07-22T18:53:30.032Z",
      "data_atualizacao": "2025-07-22T18:53:30.032Z"
    }
  },
  {
    "model": "militares.previsaovaga",
    "pk": 12,
    "fields": {
      "posto": "2T",
      "quadro": "ENG",
      "efetivo_atual": 0,
      "efetivo_previsto": 2,
      "vagas_disponiveis": 2,
      "vagas_fixadas": 0,
      "observacoes_vagas_fixadas": null,
      "ativo": true,
      "data_criacao": "2025-07-22T18:53:30.036Z",
      "data_atualizacao": "2025-07-22T18:53:30.036Z"
    }
  },
  {
    "model": "militares.previsaovaga",
    "pk": 13,
    "fields": {
      "posto": "CP",
      "quadro": "ENG",
      "efetivo_atual": 2,
      "efetivo_previsto": 2,
      "vagas_disponiveis": 0,
      "vagas_fixadas": 0,
      "observacoes_vagas_fixadas": null,
      "ativo": true,
      "data_criacao": "2025-07-22T18:53:30.040Z",
      "data_atualizacao": "2025-07-25T15:48:24.373Z"
    }
  },
  {
    "model": "militares.previsaovaga",
    "pk": 14,
    "fields": {
      "posto": "MJ",
      "quadro": "ENG",
      "efetivo_atual": 0,
      "efetivo_previsto": 2,
      "vagas_disponiveis": 2,
      "vagas_fixadas": 0,
      "observacoes_vagas_fixadas": null,
      "ativo": true,
      "data_criacao": "2025-07-22T18:53:30.042Z",
      "data_atualizacao": "2025-07-22T18:53:30.042Z"
    }
  },
  {
    "model": "militares.previsaovaga",
    "pk": 15,
    "fields": {
      "posto": "TC",
      "quadro": "ENG",
      "efetivo_atual": 0,
      "efetivo_previsto": 2,
      "vagas_disponiveis": 2,
      "vagas_fixadas": 0,
      "observacoes_vagas_fixadas": null,
      "ativo": true,
      "data_criacao": "2025-07-22T18:53:30.042Z",
      "data_atualizacao": "2025-07-22T18:53:30.042Z"
    }
  },
  {
    "model": "militares.previsaovaga",
    "pk": 16,
    "fields": {
      "posto": "1S",
      "quadro": "PRACAS",
      "efetivo_atual": 25,
      "efetivo_previsto": 102,
      "vagas_disponiveis": 77,
      "vagas_fixadas": 0,
      "observacoes_vagas_fixadas": null,
      "ativo": true,
      "data_criacao": "2025-07-22T18:53:30.042Z",
      "data_atualizacao": "2025-07-25T15:51:22.754Z"
    }
  },
  {
    "model": "militares.previsaovaga",
    "pk": 17,
    "fields": {
      "posto": "2S",
      "quadro": "PRACAS",
      "efetivo_atual": 16,
      "efetivo_previsto": 130,
      "vagas_disponiveis": 114,
      "vagas_fixadas": 0,
      "observacoes_vagas_fixadas": null,
      "ativo": true,
      "data_criacao": "2025-07-22T18:53:30.048Z",
      "data_atualizacao": "2025-07-25T15:51:37.977Z"
    }
  },
  {
    "model": "militares.previsaovaga",
    "pk": 18,
    "fields": {
      "posto": "3S",
      "quadro": "PRACAS",
      "efetivo_atual": 10,
      "efetivo_previsto": 150,
      "vagas_disponiveis": 140,
      "vagas_fixadas": 0,
      "observacoes_vagas_fixadas": null,
      "ativo": true,
      "data_criacao": "2025-07-22T18:53:30.050Z",
      "data_atualizacao": "2025-07-25T15:51:47.774Z"
    }
  },
  {
    "model": "militares.previsaovaga",
    "pk": 19,
    "fields": {
      "posto": "CAB",
      "quadro": "PRACAS",
      "efetivo_atual": 51,
      "efetivo_previsto": 240,
      "vagas_disponiveis": 189,
      "vagas_fixadas": 0,
      "observacoes_vagas_fixadas": null,
      "ativo": true,
      "data_criacao": "2025-07-22T18:53:30.052Z",
      "data_atualizacao": "2025-07-25T15:52:38.253Z"
    }
  },
  {
    "model": "militares.previsaovaga",
    "pk": 20,
    "fields": {
      "posto": "SD",
      "quadro": "PRACAS",
      "efetivo_atual": 194,
      "efetivo_previsto": 428,
      "vagas_disponiveis": 234,
      "vagas_fixadas": 0,
      "observacoes_vagas_fixadas": null,
      "ativo": true,
      "data_criacao": "2025-07-22T18:53:30.058Z",
      "data_atualizacao": "2025-07-25T15:55:57.384Z"
    }
  },
  {
    "model": "militares.previsaovaga",
    "pk": 21,
    "fields": {
      "posto": "ST",
      "quadro": "PRACAS",
      "efetivo_atual": 56,
      "efetivo_previsto": 63,
      "vagas_disponiveis": 7,
      "vagas_fixadas": 0,
      "observacoes_vagas_fixadas": null,
      "ativo": true,
      "data_criacao": "2025-07-22T18:53:30.058Z",
      "data_atualizacao": "2025-07-25T15:50:58.037Z"
    }
  },
  {
    "model": "militares.previsaovaga",
    "pk": 22,
    "fields": {
      "posto": "1T",
      "quadro": "SAUDE",
      "efetivo_atual": 0,
      "efetivo_previsto": 2,
      "vagas_disponiveis": 2,
      "vagas_fixadas": 0,
      "observacoes_vagas_fixadas": null,
      "ativo": true,
      "data_criacao": "2025-07-22T18:53:30.060Z",
      "data_atualizacao": "2025-07-22T18:53:30.060Z"
    }
  },
  {
    "model": "militares.previsaovaga",
    "pk": 23,
    "fields": {
      "posto": "2T",
      "quadro": "SAUDE",
      "efetivo_atual": 0,
      "efetivo_previsto": 6,
      "vagas_disponiveis": 6,
      "vagas_fixadas": 0,
      "observacoes_vagas_fixadas": null,
      "ativo": true,
      "data_criacao": "2025-07-22T18:53:30.062Z",
      "data_atualizacao": "2025-07-22T18:53:30.062Z"
    }
  },
  {
    "model": "militares.previsaovaga",
    "pk": 24,
    "fields": {
      "posto": "CP",
      "quadro": "SAUDE",
      "efetivo_atual": 0,
      "efetivo_previsto": 2,
      "vagas_disponiveis": 2,
      "vagas_fixadas": 0,
      "observacoes_vagas_fixadas": null,
      "ativo": true,
      "data_criacao": "2025-07-22T18:53:30.064Z",
      "data_atualizacao": "2025-07-22T18:53:30.064Z"
    }
  },
  {
    "model": "militares.previsaovaga",
    "pk": 25,
    "fields": {
      "posto": "MJ",
      "quadro": "SAUDE",
      "efetivo_atual": 0,
      "efetivo_previsto": 1,
      "vagas_disponiveis": 1,
      "vagas_fixadas": 0,
      "observacoes_vagas_fixadas": null,
      "ativo": true,
      "data_criacao": "2025-07-22T18:53:30.065Z",
      "data_atualizacao": "2025-07-22T18:53:30.065Z"
    }
  },
  {
    "model": "militares.previsaovaga",
    "pk": 26,
    "fields": {
      "posto": "TC",
      "quadro": "SAUDE",
      "efetivo_atual": 0,
      "efetivo_previsto": 1,
      "vagas_disponiveis": 1,
      "vagas_fixadas": 0,
      "observacoes_vagas_fixadas": null,
      "ativo": true,
      "data_criacao": "2025-07-22T18:53:30.069Z",
      "data_atualizacao": "2025-07-22T18:53:30.069Z"
    }
  }
]